netbook/__init__.py
netbook/_cell.py
netbook/_find.py
netbook/_ipykernel_init.py
netbook/_text_area.py
netbook/_textual_app.py
netbook/netbook.css
netbook-0.6.2.dist-info/METADATA
netbook-0.6.2.dist-info/WHEEL
netbook-0.6.2.dist-info/entry_points.txt
netbook-0.6.2.dist-info/licenses/LICENSE
netbook-0.6.2.dist-info/RECORD
