Metadata-Version: 2.4
Name: netbook
Version: 0.6.2
Summary: Jupyter notebook for terminal
Project-URL: homepage, https://github.com/lyovushka/netbook
Author-email: haykazyan@zoho.com
License-Expression: MIT
License-File: LICENSE
Requires-Python: >=3.11
Requires-Dist: appnope==0.1.4; sys_platform == 'darwin'
Requires-Dist: asttokens==3.0.1
Requires-Dist: attrs==25.4.0
Requires-Dist: cffi==2.0.0
Requires-Dist: colorama==0.4.6; sys_platform == 'win32'
Requires-Dist: comm==0.2.3
Requires-Dist: debugpy==1.8.17
Requires-Dist: decorator==5.2.1
Requires-Dist: executing==2.2.1
Requires-Dist: fastjsonschema==2.21.2
Requires-Dist: ipykernel==7.1.0
Requires-Dist: ipython-pygments-lexers==1.1.1
Requires-Dist: ipython==9.7.0
Requires-Dist: jedi==0.19.2
Requires-Dist: jsonschema-specifications==2025.9.1
Requires-Dist: jsonschema==4.25.1
Requires-Dist: jupyter-client==8.6.3
Requires-Dist: jupyter-core==5.9.1
Requires-Dist: linkify-it-py==2.0.3
Requires-Dist: markdown-it-py==4.0.0
Requires-Dist: matplotlib-inline==0.2.1
Requires-Dist: mdit-py-plugins==0.5.0
Requires-Dist: mdurl==0.1.2
Requires-Dist: nbformat==5.10.4
Requires-Dist: nest-asyncio==1.6.0
Requires-Dist: packaging==25.0
Requires-Dist: parso==0.8.5
Requires-Dist: pexpect==4.9.0; sys_platform != 'emscripten' and sys_platform != 'win32'
Requires-Dist: pillow==12.0.0
Requires-Dist: platformdirs==4.5.0
Requires-Dist: prompt-toolkit==3.0.52
Requires-Dist: psutil==7.1.3
Requires-Dist: ptyprocess==0.7.0; sys_platform != 'emscripten' and sys_platform != 'win32'
Requires-Dist: pure-eval==0.2.3
Requires-Dist: pycparser==2.23; implementation_name != 'PyPy'
Requires-Dist: pygments==2.19.2
Requires-Dist: python-dateutil==2.9.0.post0
Requires-Dist: pyvips-binary==8.17.3
Requires-Dist: pyvips[binary]==3.0.0
Requires-Dist: pyzmq==27.1.0
Requires-Dist: referencing==0.37.0
Requires-Dist: rich==14.2.0
Requires-Dist: rpds-py==0.28.0
Requires-Dist: six==1.17.0
Requires-Dist: stack-data==0.6.3
Requires-Dist: textual-image[textual]==0.8.4
Requires-Dist: textual[syntax]==6.11.0
Requires-Dist: tornado==6.5.2
Requires-Dist: traitlets==5.14.3
Requires-Dist: tree-sitter-bash==0.25.0
Requires-Dist: tree-sitter-css==0.25.0
Requires-Dist: tree-sitter-go==0.25.0
Requires-Dist: tree-sitter-html==0.23.2
Requires-Dist: tree-sitter-java==0.23.5
Requires-Dist: tree-sitter-javascript==0.25.0
Requires-Dist: tree-sitter-json==0.24.8
Requires-Dist: tree-sitter-markdown==0.5.1
Requires-Dist: tree-sitter-python==0.25.0
Requires-Dist: tree-sitter-regex==0.25.0
Requires-Dist: tree-sitter-rust==0.24.0
Requires-Dist: tree-sitter-sql==0.3.11
Requires-Dist: tree-sitter-toml==0.7.0
Requires-Dist: tree-sitter-xml==0.7.0
Requires-Dist: tree-sitter-yaml==0.7.2
Requires-Dist: tree-sitter==0.25.2
Requires-Dist: typing-extensions==4.15.0
Requires-Dist: uc-micro-py==1.0.3
Requires-Dist: wcwidth==0.2.14
